{
  "attributes": [
    {
      "allow_nil?": false,
      "default": "fragment(\"gen_random_uuid()\")",
      "generated?": false,
      "precision": null,
      "primary_key?": true,
      "references": null,
      "scale": null,
      "size": null,
      "source": "id",
      "type": "uuid"
    },
    {
      "allow_nil?": false,
      "default": "nil",
      "generated?": false,
      "precision": null,
      "primary_key?": false,
      "references": null,
      "scale": null,
      "size": null,
      "source": "email",
      "type": "citext"
    },
    {
      "allow_nil?": true,
      "default": "nil",
      "generated?": false,
      "precision": null,
      "primary_key?": false,
      "references": null,
      "scale": null,
      "size": null,
      "source": "first_name",
      "type": "text"
    },
    {
      "allow_nil?": true,
      "default": "nil",
      "generated?": false,
      "precision": null,
      "primary_key?": false,
      "references": null,
      "scale": null,
      "size": null,
      "source": "last_name",
      "type": "text"
    },
    {
      "allow_nil?": true,
      "default": "nil",
      "generated?": false,
      "precision": null,
      "primary_key?": false,
      "references": null,
      "scale": null,
      "size": null,
      "source": "phone",
      "type": "text"
    },
    {
      "allow_nil?": true,
      "default": "nil",
      "generated?": false,
      "precision": null,
      "primary_key?": false,
      "references": null,
      "scale": null,
      "size": null,
      "source": "shipping_address",
      "type": "map"
    },
    {
      "allow_nil?": true,
      "default": "nil",
      "generated?": false,
      "precision": null,
      "primary_key?": false,
      "references": null,
      "scale": null,
      "size": null,
      "source": "billing_address",
      "type": "map"
    },
    {
      "allow_nil?": true,
      "default": "[]",
      "generated?": false,
      "precision": null,
      "primary_key?": false,
      "references": null,
      "scale": null,
      "size": null,
      "source": "saved_payment_methods",
      "type": [
        "array",
        "map"
      ]
    },
    {
      "allow_nil?": true,
      "default": "0",
      "generated?": false,
      "precision": null,
      "primary_key?": false,
      "references": null,
      "scale": null,
      "size": null,
      "source": "total_orders",
      "type": "bigint"
    },
    {
      "allow_nil?": true,
      "default": "\"0\"",
      "generated?": false,
      "precision": null,
      "primary_key?": false,
      "references": null,
      "scale": null,
      "size": null,
      "source": "total_spent",
      "type": "decimal"
    },
    {
      "allow_nil?": false,
      "default": "\"active\"",
      "generated?": false,
      "precision": null,
      "primary_key?": false,
      "references": null,
      "scale": null,
      "size": null,
      "source": "status",
      "type": "text"
    },
    {
      "allow_nil?": true,
      "default": "%{}",
      "generated?": false,
      "precision": null,
      "primary_key?": false,
      "references": null,
      "scale": null,
      "size": null,
      "source": "marketing_preferences",
      "type": "map"
    },
    {
      "allow_nil?": true,
      "default": "nil",
      "generated?": false,
      "precision": null,
      "primary_key?": false,
      "references": null,
      "scale": null,
      "size": null,
      "source": "loyalty_tier",
      "type": "text"
    },
    {
      "allow_nil?": true,
      "default": "0",
      "generated?": false,
      "precision": null,
      "primary_key?": false,
      "references": null,
      "scale": null,
      "size": null,
      "source": "loyalty_points",
      "type": "bigint"
    },
    {
      "allow_nil?": true,
      "default": "nil",
      "generated?": false,
      "precision": null,
      "primary_key?": false,
      "references": null,
      "scale": null,
      "size": null,
      "source": "tags",
      "type": [
        "array",
        "text"
      ]
    },
    {
      "allow_nil?": true,
      "default": "nil",
      "generated?": false,
      "precision": null,
      "primary_key?": false,
      "references": null,
      "scale": null,
      "size": null,
      "source": "last_active_at",
      "type": "utc_datetime"
    },
    {
      "allow_nil?": true,
      "default": "nil",
      "generated?": false,
      "precision": null,
      "primary_key?": false,
      "references": null,
      "scale": null,
      "size": null,
      "source": "source",
      "type": "text"
    },
    {
      "allow_nil?": true,
      "default": "false",
      "generated?": false,
      "precision": null,
      "primary_key?": false,
      "references": null,
      "scale": null,
      "size": null,
      "source": "gdpr_consent",
      "type": "boolean"
    },
    {
      "allow_nil?": true,
      "default": "nil",
      "generated?": false,
      "precision": null,
      "primary_key?": false,
      "references": null,
      "scale": null,
      "size": null,
      "source": "gdpr_consent_at",
      "type": "utc_datetime"
    },
    {
      "allow_nil?": false,
      "default": "fragment(\"(now() AT TIME ZONE 'utc')\")",
      "generated?": false,
      "precision": null,
      "primary_key?": false,
      "references": null,
      "scale": null,
      "size": null,
      "source": "inserted_at",
      "type": "utc_datetime_usec"
    },
    {
      "allow_nil?": false,
      "default": "fragment(\"(now() AT TIME ZONE 'utc')\")",
      "generated?": false,
      "precision": null,
      "primary_key?": false,
      "references": null,
      "scale": null,
      "size": null,
      "source": "updated_at",
      "type": "utc_datetime_usec"
    },
    {
      "allow_nil?": false,
      "default": "nil",
      "generated?": false,
      "precision": null,
      "primary_key?": true,
      "references": {
        "deferrable": false,
        "destination_attribute": "id",
        "destination_attribute_default": null,
        "destination_attribute_generated": null,
        "index?": false,
        "match_type": null,
        "match_with": null,
        "multitenancy": {
          "attribute": null,
          "global": false,
          "strategy": "context"
        },
        "name": "customers_merchant_id_fkey",
        "on_delete": null,
        "on_update": null,
        "primary_key?": true,
        "schema": "public",
        "table": "merchants"
      },
      "scale": null,
      "size": null,
      "source": "merchant_id",
      "type": "uuid"
    },
    {
      "allow_nil?": true,
      "default": "nil",
      "generated?": false,
      "precision": null,
      "primary_key?": false,
      "references": {
        "deferrable": false,
        "destination_attribute": "id",
        "destination_attribute_default": null,
        "destination_attribute_generated": null,
        "index?": false,
        "match_type": null,
        "match_with": null,
        "multitenancy": {
          "attribute": null,
          "global": null,
          "strategy": null
        },
        "name": "customers_user_id_fkey",
        "on_delete": null,
        "on_update": null,
        "primary_key?": true,
        "schema": "platform",
        "table": "users"
      },
      "scale": null,
      "size": null,
      "source": "user_id",
      "type": "uuid"
    }
  ],
  "base_filter": null,
  "check_constraints": [],
  "custom_indexes": [],
  "custom_statements": [],
  "has_create_action": true,
  "hash": "1A6717F27471500B35ECC1923C7D2AC5DAEAF0415F50C5E1A84F0A9D716F4B19",
  "identities": [],
  "multitenancy": {
    "attribute": null,
    "global": false,
    "strategy": "context"
  },
  "repo": "Elixir.Mcp.Repo",
  "schema": null,
  "table": "customers"
}